pypackerdetect/VERSION.txt
pypackerdetect/__info__.py
pypackerdetect/__init__.py
pypackerdetect/__main__.py
pypackerdetect/db/packers.json
pypackerdetect/db/sections.json
pypackerdetect/db/sigs_long.txt
pypackerdetect/db/sigs_short.txt
pypackerdetect-1.1.3.dist-info/LICENSE
pypackerdetect-1.1.3.dist-info/METADATA
pypackerdetect-1.1.3.dist-info/WHEEL
pypackerdetect-1.1.3.dist-info/entry_points.txt
pypackerdetect-1.1.3.dist-info/top_level.txt
pypackerdetect-1.1.3.dist-info/RECORD
