Metadata-Version: 2.1
Name: pypackerdetect
Version: 1.1.3
Summary: Re-implementation and packaging of PyPackerDetect
Author-email: Alexandre D'Hondt <alexandre.dhondt@gmail.com>
License:                     GNU GENERAL PUBLIC LICENSE
Project-URL: homepage, https://github.com/packing-box/pypackerdetect
Project-URL: issues, https://github.com/packing-box/pypackerdetect/issues
Project-URL: repository, https://github.com/packing-box/pypackerdetect
Keywords: packing,packed-executable,packing-detection,pe
Classifier: Development Status :: 5 - Production/Stable
Classifier: Environment :: Console
Classifier: Intended Audience :: Developers
Classifier: Intended Audience :: Information Technology
Classifier: Intended Audience :: Other Audience
Classifier: License :: OSI Approved :: GNU General Public License v3 or later (GPLv3+)
Classifier: Programming Language :: Python :: 3
Classifier: Topic :: Software Development :: Libraries :: Python Modules
Classifier: Topic :: Security
Requires-Python: <4,>=3.8
License-File: LICENSE
Requires-Dist: pefile
Requires-Dist: peid>=2.2.1
